<Asset>
  <Template>NewspaperArticle</Template>
  <Values>
    <Standard>
      <GUID>141686</GUID>
      <Name>Propaganda Armament Strong</Name>
    </Standard>
    <NewspaperArticle>
      <Headline>14895</Headline>
      <Subline>14896</Subline>
      <Image>142288</Image>
      <NewsPriority>
        <StartValue>9</StartValue>
        <LossOnPublish>0</LossOnPublish>
        <RecoveryByInterval>0</RecoveryByInterval>
        <GainByNotPublished>0</GainByNotPublished>
        <Minimum>0</Minimum>
        <Maximum>0</Maximum>
      </NewsPriority>
      <ArticleType>Propaganda</ArticleType>
      <ArticleEffect>WarPreparation</ArticleEffect>
      <EffectValue>150</EffectValue>
      <ArticleEffects>
        <Item>
          <ArticleEffect>WarPreparation</ArticleEffect>
          <ArticleValue>150</ArticleValue>
        </Item>
      </ArticleEffects>
      <EffectStrength>Strong</EffectStrength>
      <InfluenceCosts>120</InfluenceCosts>
      <ArticleName>14042</ArticleName>
    </NewspaperArticle>
    <Locked>
      <DefaultLockedState>1</DefaultLockedState>
    </Locked>
    <Trigger>
      <TriggerCondition>
        <Template>ConditionPlayerCounter</Template>
        <Values>
          <Condition />
          <ConditionPlayerCounter>
            <PlayerCounter>CorporationLevel</PlayerCounter>
            <CounterAmount>30</CounterAmount>
          </ConditionPlayerCounter>
        </Values>
      </TriggerCondition>
      <TriggerActions>
        <Item>
          <TriggerAction>
            <Template>ActionUnlockAsset</Template>
            <Values>
              <Action />
              <ActionUnlockAsset>
                <UnhideAssets>
                  <Item />
                </UnhideAssets>
              </ActionUnlockAsset>
            </Values>
          </TriggerAction>
        </Item>
      </TriggerActions>
    </Trigger>
    <TriggerSetup>
      <AutoRegisterTrigger>1</AutoRegisterTrigger>
      <AutoSelfUnlock>1</AutoSelfUnlock>
    </TriggerSetup>
  </Values>
</Asset>