<Asset>
  <Template>A7_QuestPicturePuzzleObject</Template>
  <Values>
    <Standard>
      <GUID>110784</GUID>
      <Name>Picture Puzzle - Cure by work - Hugo Mercier </Name>
      <ID>Quest_DM_4</ID>
    </Standard>
    <Quest>
      <InvitationMessage>
        <Notification>
          <IsBaseAutoCreateAsset>1</IsBaseAutoCreateAsset>
          <Values>
            <CharacterNotification />
            <BaseNotification />
            <NotificationSubtitle>
              <SubtitleGroup>-771545229</SubtitleGroup>
            </NotificationSubtitle>
          </Values>
        </Notification>
      </InvitationMessage>
      <OnQuestActive>
        <IsBaseAutoCreateAsset>1</IsBaseAutoCreateAsset>
        <Values>
          <ActionList>
            <Actions>
              <Item>
                <Action>
                  <Template>ActionSpawnObjects</Template>
                  <Values>
                    <Action />
                    <ActionSpawnObjects>
                      <SpawnGUID>110785</SpawnGUID>
                      <Amount>1</Amount>
                      <DoSetVisualSpawnOwner>1</DoSetVisualSpawnOwner>
                      <VisualSpawnOwner>Second_ai_11_Mercier</VisualSpawnOwner>
                    </ActionSpawnObjects>
                    <SpawnArea>
                      <SpawnContext>Object</SpawnContext>
                      <ContextGUID>110669</ContextGUID>
                      <SpawnAreaType>Mountain_01</SpawnAreaType>
                      <DistanceToContext>100</DistanceToContext>
                    </SpawnArea>
                    <SessionFilter>
                      <Sessions>
                        <Item>
                          <Session>180023</Session>
                        </Item>
                      </Sessions>
                    </SessionFilter>
                  </Values>
                </Action>
              </Item>
            </Actions>
          </ActionList>
        </Values>
      </OnQuestActive>
      <OnQuestEnd>
        <IsBaseAutoCreateAsset>1</IsBaseAutoCreateAsset>
        <Values>
          <ActionList>
            <Actions>
              <Item>
                <Action>
                  <Template>ActionDeleteObjects</Template>
                  <Values>
                    <Action />
                    <ActionDeleteObjects />
                    <ObjectFilter>
                      <ObjectGUID>110785</ObjectGUID>
                    </ObjectFilter>
                  </Values>
                </Action>
              </Item>
            </Actions>
          </ActionList>
        </Values>
      </OnQuestEnd>
      <QuestGiver>220</QuestGiver>
      <StoryText>111528</StoryText>
      <QuestActivation>ConfirmationDialog</QuestActivation>
      <NeededProgressLevel>MidGame;LateMidGame;LateGame;EndGame</NeededProgressLevel>
      <DelayTimer>1200000</DelayTimer>
      <QuestSessionDependencies>
        <Item>
          <SessionOrRegion>180023</SessionOrRegion>
        </Item>
      </QuestSessionDependencies>
      <ReputationQuestFail>
        <ReputationFailList>
          <Item>
            <VectorElement>
              <InheritedIndex>0</InheritedIndex>
              <InheritanceMapV2>
                <Entry>
                  <TemplateName>Quest</TemplateName>
                  <Index>0</Index>
                </Entry>
                <Entry>
                  <TemplateName>A7_QuestStatusQuo</TemplateName>
                  <Index>0</Index>
                </Entry>
                <Entry>
                  <TemplateName>A7_QuestPicturePuzzleObject</TemplateName>
                  <Index>0</Index>
                </Entry>
              </InheritanceMapV2>
            </VectorElement>
            <ReputationParticipant>Second_ai_11_Mercier</ReputationParticipant>
            <ReputationAmount>-4</ReputationAmount>
          </Item>
        </ReputationFailList>
      </ReputationQuestFail>
      <ReputationQuestDeclined>
        <ReputationDeclinedList>
          <Item>
            <ReputationParticipant>Second_ai_11_Mercier</ReputationParticipant>
            <ReputationAmount>-3</ReputationAmount>
          </Item>
        </ReputationDeclinedList>
      </ReputationQuestDeclined>
      <QuestHints>
        <Item>
          <Text>111998</Text>
        </Item>
      </QuestHints>
      <StarterSpeechBubble>
        <IsBaseAutoCreateAsset>1</IsBaseAutoCreateAsset>
        <Values>
          <Condition />
          <ConditionTutorialInteraction>
            <HintText>111505</HintText>
            <ObjectFilter>
              <IsBaseAutoCreateAsset>1</IsBaseAutoCreateAsset>
              <Values>
                <ObjectFilter>
                  <ObjectGUID>110688</ObjectGUID>
                </ObjectFilter>
              </Values>
            </ObjectFilter>
            <UseSpecificPortrait>1</UseSpecificPortrait>
            <SpecificPortraitProfile>220</SpecificPortraitProfile>
          </ConditionTutorialInteraction>
        </Values>
      </StarterSpeechBubble>
      <SuccessSpeechBubble>
        <IsBaseAutoCreateAsset>1</IsBaseAutoCreateAsset>
        <Values>
          <Condition />
          <ConditionTutorialInteraction>
            <ObjectFilter>
              <IsBaseAutoCreateAsset>1</IsBaseAutoCreateAsset>
              <Values>
                <ObjectFilter>
                  <ObjectGUID>110688</ObjectGUID>
                </ObjectFilter>
              </Values>
            </ObjectFilter>
            <UseSpecificPortrait>1</UseSpecificPortrait>
            <SpecificPortraitProfile>220</SpecificPortraitProfile>
          </ConditionTutorialInteraction>
        </Values>
      </SuccessSpeechBubble>
    </Quest>
    <PreConditionList>
      <Condition>
        <IsBaseAutoCreateAsset>1</IsBaseAutoCreateAsset>
        <Values>
          <Condition />
          <ConditionAlwaysTrue />
        </Values>
      </Condition>
    </PreConditionList>
    <Text>
      <LocaText>
        <English>
          <Text>The Work Cure</Text>
          <Status>Exported</Status>
          <ExportCount>1</ExportCount>
        </English>
      </LocaText>
      <LineID>31376</LineID>
    </Text>
    <Reward>
      <RewardAssets>
        <Item>
          <Reward>150038</Reward>
          <Amount>1</Amount>
        </Item>
      </RewardAssets>
      <RewardReputation>
        <Item>
          <VectorElement>
            <InheritedIndex>0</InheritedIndex>
            <InheritanceMapV2>
              <Entry>
                <TemplateName>Quest</TemplateName>
                <Index>0</Index>
              </Entry>
              <Entry>
                <TemplateName>A7_QuestStatusQuo</TemplateName>
                <Index>0</Index>
              </Entry>
              <Entry>
                <TemplateName>A7_QuestPicturePuzzleObject</TemplateName>
                <Index>0</Index>
              </Entry>
            </InheritanceMapV2>
          </VectorElement>
          <ReputationParticipant>Second_ai_11_Mercier</ReputationParticipant>
          <ReputationAmount>5</ReputationAmount>
        </Item>
        <Item>
          <ReputationParticipant>Second_ai_01_Jorgensen</ReputationParticipant>
          <ReputationAmount>-2</ReputationAmount>
        </Item>
        <Item>
          <ReputationParticipant>Second_ai_07_von_Malching</ReputationParticipant>
          <ReputationAmount>2</ReputationAmount>
        </Item>
      </RewardReputation>
    </Reward>
    <Objectives>
      <WinConditions>
        <Item>
          <VectorElement>
            <InheritedIndex>0</InheritedIndex>
            <InheritanceMapV2>
              <Entry>
                <TemplateName>A7_QuestPicturePuzzleObject</TemplateName>
                <Index>0</Index>
              </Entry>
            </InheritanceMapV2>
          </VectorElement>
          <Objective>
            <IsBaseAutoCreateAsset>1</IsBaseAutoCreateAsset>
            <Values>
              <ConditionQuestPicturePuzzle>
                <PicturePuzzleObjects>
                  <Item>
                    <Object>110783</Object>
                    <Amount>3</Amount>
                    <AdditionalAmount>5</AdditionalAmount>
                    <Context>
                      <SpawnArea>
                        <Template>QuestSpawnArea</Template>
                        <Values>
                          <SpawnArea>
                            <SpawnContext>Object</SpawnContext>
                            <MatcherGUID>110747</MatcherGUID>
                            <DistanceToContext>1</DistanceToContext>
                            <MinObjectDistance>5</MinObjectDistance>
                            <MaxObjectDistance>15</MaxObjectDistance>
                          </SpawnArea>
                        </Values>
                      </SpawnArea>
                    </Context>
                  </Item>
                </PicturePuzzleObjects>
              </ConditionQuestPicturePuzzle>
              <ConditionQuestObjective />
              <ConditionPropsSessionSettings />
              <ConditionPropsExecutionPlaceSettings>
                <ExecutionPlaceConfirmOnReached>0</ExecutionPlaceConfirmOnReached>
              </ConditionPropsExecutionPlaceSettings>
            </Values>
          </Objective>
        </Item>
        <Item>
          <Objective>
            <Template>SelectObjectObjective</Template>
            <Values>
              <ConditionQuestObjective />
              <ConditionQuestSelectObject>
                <SelectObjects>
                  <Item>
                    <Object>
                      <Template>ObjectFilter</Template>
                      <Values>
                        <ObjectFilter>
                          <ObjectGUID>110785</ObjectGUID>
                          <ObjectSession>180023</ObjectSession>
                        </ObjectFilter>
                      </Values>
                    </Object>
                  </Item>
                </SelectObjects>
              </ConditionQuestSelectObject>
              <ConditionPropsSessionSettings />
              <ConditionPropsExecutionPlaceSettings>
                <ExecutionPlaceConfirmOnReached>0</ExecutionPlaceConfirmOnReached>
              </ConditionPropsExecutionPlaceSettings>
            </Values>
          </Objective>
        </Item>
      </WinConditions>
      <WinConditionCompletionOrder>Linear</WinConditionCompletionOrder>
    </Objectives>
    <QuestOptional>
      <HasStarterObject>Specific</HasStarterObject>
      <StarterObject>
        <IsBaseAutoCreateAsset>1</IsBaseAutoCreateAsset>
        <Values>
          <Condition />
          <ConditionStarterObject>
            <StarterObjectObject>
              <Template>ConditionObjectSpawnedObject</Template>
              <Values>
                <ConditionObjectSpawnedObject>
                  <ExecutionObject>110688</ExecutionObject>
                  <ObjectSpawnArea>
                    <IsBaseAutoCreateAsset>1</IsBaseAutoCreateAsset>
                    <Values>
                      <SpawnArea>
                        <SpawnContext>PlayerKontor</SpawnContext>
                        <DistanceToContext>30</DistanceToContext>
                      </SpawnArea>
                    </Values>
                  </ObjectSpawnArea>
                  <DoSetVisualObjectOwner>1</DoSetVisualObjectOwner>
                  <VisualObjectOwner>Second_ai_11_Mercier</VisualObjectOwner>
                </ConditionObjectSpawnedObject>
                <ConditionScanner />
                <ConditionObjectiveSignsAndFeedback>
                  <Infolayer>500173</Infolayer>
                </ConditionObjectiveSignsAndFeedback>
              </Values>
            </StarterObjectObject>
          </ConditionStarterObject>
          <ConditionQuestObjective />
          <ConditionPropsSessionSettings />
        </Values>
      </StarterObject>
    </QuestOptional>
  </Values>
</Asset>