<Asset>
  <Template>RewardPool</Template>
  <Values>
    <Standard>
      <GUID>191150</GUID>
      <Name>Sunken Depths Reward Pool</Name>
    </Standard>
    <RewardPool>
      <ItemsPool>
        <Item>
          <ItemLink>192966</ItemLink>
          <Weight>50</Weight>
        </Item>
        <Item>
          <ItemLink>192967</ItemLink>
          <Weight>100</Weight>
        </Item>
        <Item>
          <ItemLink>192968</ItemLink>
          <Weight>50</Weight>
        </Item>
        <Item>
          <ItemLink>192969</ItemLink>
          <Weight>25</Weight>
        </Item>
      </ItemsPool>
      <IgnoreUnlocks>1</IgnoreUnlocks>
    </RewardPool>
    <Locked />
    <Text />
  </Values>
</Asset>