<Asset>
  <Template>StateGroup</Template>
  <Values>
    <Standard>
      <GUID>203372</GUID>
      <Name>ST_screen</Name>
      <IconFilename>test_data/graphics/wwise_icons/state_group.png</IconFilename>
    </Standard>
    <WwiseStandard>
      <WwiseID>3799715075</WwiseID>
    </WwiseStandard>
    <StateGroup>
      <StateChoices>
        <Item>
          <Choice>203364</Choice>
        </Item>
        <Item>
          <Choice>203365</Choice>
        </Item>
        <Item>
          <Choice>203366</Choice>
        </Item>
        <Item>
          <Choice>203367</Choice>
        </Item>
        <Item>
          <Choice>203368</Choice>
        </Item>
        <Item>
          <Choice>203369</Choice>
        </Item>
        <Item>
          <Choice>203370</Choice>
        </Item>
        <Item>
          <Choice>203371</Choice>
        </Item>
        <Item>
          <Choice>216049</Choice>
        </Item>
        <Item>
          <Choice>226707</Choice>
        </Item>
        <Item>
          <Choice>226708</Choice>
        </Item>
        <Item>
          <Choice>236639</Choice>
        </Item>
        <Item>
          <Choice>239686</Choice>
        </Item>
        <Item>
          <Choice>239687</Choice>
        </Item>
        <Item>
          <Choice>239688</Choice>
        </Item>
        <Item>
          <Choice>239689</Choice>
        </Item>
        <Item>
          <Choice>239690</Choice>
        </Item>
        <Item>
          <Choice>239691</Choice>
        </Item>
        <Item>
          <Choice>239692</Choice>
        </Item>
        <Item>
          <Choice>239997</Choice>
        </Item>
        <Item>
          <Choice>200784</Choice>
        </Item>
        <Item>
          <Choice>200786</Choice>
        </Item>
        <Item>
          <Choice>200818</Choice>
        </Item>
        <Item>
          <Choice>200922</Choice>
        </Item>
      </StateChoices>
    </StateGroup>
  </Values>
</Asset>