<Asset>
  <Template>AudioText</Template>
  <Values>
    <Text>
      <LocaText>
        <English>
          <Text>Brrrrrrrrrrr.</Text>
          <Status>Exported</Status>
          <ExportCount>1</ExportCount>
        </English>
      </LocaText>
      <LineID>34135</LineID>
    </Text>
    <AudioText>
      <AudioAsset>245082</AudioAsset>
      <Mood>Negative</Mood>
    </AudioText>
    <Standard>
      <GUID>115641</GUID>
      <Name>AT_DLC03_res1_Cold4</Name>
    </Standard>
  </Values>
</Asset>