<Asset>
  <Template>AudioText</Template>
  <Values>
    <Text>
      <LocaText>
        <English>
          <Text>Hold hard! A craig, heaped by highland hand, is well worth our time.</Text>
          <Status>Exported</Status>
          <ExportCount>1</ExportCount>
        </English>
      </LocaText>
      <LineID>33729</LineID>
    </Text>
    <AudioText>
      <AudioAsset>245125</AudioAsset>
      <SpeechAudioType>Campaign</SpeechAudioType>
      <Mood>Positve</Mood>
    </AudioText>
    <Standard>
      <GUID>116451</GUID>
      <Name>AT_DLC03_LadyFaithful_ArcticQ102_03</Name>
    </Standard>
  </Values>
</Asset>