<Asset>
  <Template>AudioText</Template>
  <Values>
    <Text>
      <LocaText>
        <English>
          <Text>No country benefits from long wars.</Text>
          <Status>Exported</Status>
          <ExportCount>1</ExportCount>
        </English>
      </LocaText>
      <LineID>9319</LineID>
    </Text>
    <AudioText>
      <AudioAsset>221423</AudioAsset>
    </AudioText>
    <Standard>
      <GUID>253156</GUID>
      <Name>AT_ai02_NpcAcceptsPeace1</Name>
    </Standard>
  </Values>
</Asset>