<Asset>
  <Template>AudioText</Template>
  <Values>
    <Text>
      <LocaText>
        <English>
          <Text>Lurvely!</Text>
          <Status>Exported</Status>
          <ExportCount>1</ExportCount>
        </English>
      </LocaText>
      <LineID>4355</LineID>
    </Text>
    <AudioText>
      <AudioAsset>215244</AudioAsset>
      <Mood>Positve</Mood>
    </AudioText>
    <Standard>
      <GUID>254002</GUID>
      <Name>AT_res_tier01_GenPositiveFeedback5</Name>
    </Standard>
  </Values>
</Asset>