<Asset>
  <Template>AudioText</Template>
  <Values>
    <Text>
      <LocaText>
        <English>
          <Text>Big decisions need a big pair of slippers...</Text>
          <Status>Exported</Status>
          <ExportCount>1</ExportCount>
        </English>
      </LocaText>
      <LineID>4755</LineID>
    </Text>
    <AudioText>
      <AudioAsset>215584</AudioAsset>
      <Mood>Negative</Mood>
    </AudioText>
    <Standard>
      <GUID>254415</GUID>
      <Name>AT_res_tier05_DecisionQuestOffered1</Name>
    </Standard>
  </Values>
</Asset>