<Asset>
  <Template>AudioText</Template>
  <Values>
    <Text>
      <LocaText>
        <English>
          <Text>You've got me by the Diri-giblets, whaddya want?</Text>
          <Status>Exported</Status>
          <ExportCount>1</ExportCount>
        </English>
      </LocaText>
      <LineID>8319</LineID>
    </Text>
    <AudioText>
      <AudioAsset>221385</AudioAsset>
      <Mood>Negative</Mood>
    </AudioText>
    <Standard>
      <GUID>256903</GUID>
      <Name>AT_3rd_party_06_WelcomeToPlayer5</Name>
    </Standard>
  </Values>
</Asset>