<Asset>
  <Template>AudioText</Template>
  <Values>
    <Text>
      <LocaText>
        <English>
          <Text>This is progress at least. </Text>
          <Status>Exported</Status>
          <ExportCount>1</ExportCount>
        </English>
      </LocaText>
      <LineID>9876</LineID>
    </Text>
    <AudioText>
      <AudioAsset>223150</AudioAsset>
      <Mood>Positve</Mood>
    </AudioText>
    <Standard>
      <GUID>259837</GUID>
      <Name>AT_3rd_party_05_Generic Positive Feedback4</Name>
    </Standard>
  </Values>
</Asset>