<Asset>
  <Template>AudioText</Template>
  <Values>
    <Text>
      <LocaText>
        <English>
          <Text>Do I condemn you now, or merely give you a length of rope with which to strangle yourself?</Text>
          <Status>Exported</Status>
          <ExportCount>3</ExportCount>
        </English>
      </LocaText>
      <LineID>12328</LineID>
    </Text>
    <AudioText>
      <AudioAsset>229831</AudioAsset>
      <SpeechAudioType>Campaign</SpeechAudioType>
    </AudioText>
    <Standard>
      <GUID>261036</GUID>
      <Name>AT_3rdParty07_IdleMessageSelf1</Name>
    </Standard>
  </Values>
</Asset>