<Asset>
  <Template>AudioText</Template>
  <Values>
    <Text>
      <LocaText>
        <English>
          <Text>Believe me I share Isabel's cause, but I already have enough trouble with the Empire.</Text>
          <Status>Exported</Status>
          <ExportCount>3</ExportCount>
        </English>
      </LocaText>
      <LineID>16564</LineID>
    </Text>
    <AudioText>
      <AudioAsset>233626</AudioAsset>
      <Mood>Negative</Mood>
    </AudioText>
    <Standard>
      <GUID>261186</GUID>
      <Name>AT_3rdParty04_WelcomeCampaign</Name>
    </Standard>
  </Values>
</Asset>