<Asset>
  <Template>AudioText</Template>
  <Values>
    <Text>
      <LocaText>
        <English>
          <Text>I don't like them, and I don't like you.</Text>
          <Status>Exported</Status>
          <ExportCount>1</ExportCount>
        </English>
      </LocaText>
      <LineID>17000</LineID>
    </Text>
    <AudioText>
      <AudioAsset>233160</AudioAsset>
      <Mood>Negative</Mood>
    </AudioText>
    <Standard>
      <GUID>265590</GUID>
      <Name>AT_ai07_PositiveInteraction_NPCsFoe2</Name>
    </Standard>
  </Values>
</Asset>