<Asset>
  <Template>AudioText</Template>
  <Values>
    <Text>
      <LocaText>
        <English>
          <Text>You must have fed off my resilient aura there, driving the P-p-pyrphorians away.</Text>
          <Status>Exported</Status>
          <ExportCount>3</ExportCount>
        </English>
      </LocaText>
      <LineID>16872</LineID>
    </Text>
    <AudioText>
      <AudioAsset>234498</AudioAsset>
    </AudioText>
    <Standard>
      <GUID>266595</GUID>
      <Name>AT_ai03_WelcomeCampaignVictory</Name>
    </Standard>
  </Values>
</Asset>