<Asset>
  <Template>Audio</Template>
  <Values>
    <Standard>
      <GUID>212732</GUID>
      <Name>Play_AI_DRYWILLI_IFV_UDD_00003_01WILLI_2299</Name>
      <IconFilename>test_data/graphics/wwise_icons/event.png</IconFilename>
    </Standard>
    <Audio>
      <DurationLanguageArray>
        <English>
          <DurationMinimum>4288</DurationMinimum>
          <DurationMaximum>4288</DurationMaximum>
        </English>
        <German>
          <DurationMinimum>4264</DurationMinimum>
          <DurationMaximum>4264</DurationMaximum>
        </German>
        <French>
          <DurationMinimum>4269</DurationMinimum>
          <DurationMaximum>4269</DurationMaximum>
        </French>
        <Russian>
          <DurationMinimum>4231</DurationMinimum>
          <DurationMaximum>4231</DurationMaximum>
        </Russian>
      </DurationLanguageArray>
    </Audio>
    <WwiseStandard>
      <WwiseID>2140887531</WwiseID>
    </WwiseStandard>
  </Values>
</Asset>