<Asset>
  <Template>Audio</Template>
  <Values>
    <Standard>
      <GUID>216434</GUID>
      <Name>Play_AI_DRYBERYL_DAC_NR4_00004_01BERYL_6192</Name>
      <IconFilename>test_data/graphics/wwise_icons/event.png</IconFilename>
    </Standard>
    <Audio>
      <DurationLanguageArray>
        <English>
          <DurationMinimum>2216</DurationMinimum>
          <DurationMaximum>2216</DurationMaximum>
        </English>
        <German>
          <DurationMinimum>2742</DurationMinimum>
          <DurationMaximum>2742</DurationMaximum>
        </German>
        <French>
          <DurationMinimum>2140</DurationMinimum>
          <DurationMaximum>2140</DurationMaximum>
        </French>
        <Russian>
          <DurationMinimum>1932</DurationMinimum>
          <DurationMaximum>1932</DurationMaximum>
        </Russian>
      </DurationLanguageArray>
    </Audio>
    <WwiseStandard>
      <WwiseID>4071174870</WwiseID>
    </WwiseStandard>
  </Values>
</Asset>