<Asset>
  <Template>Audio</Template>
  <Values>
    <Standard>
      <GUID>220738</GUID>
      <Name>Play_AI_DRYEDVAR_IFV_B4H4Z_00003_01EDVAR_8732</Name>
      <IconFilename>test_data/graphics/wwise_icons/event.png</IconFilename>
    </Standard>
    <Audio>
      <DurationLanguageArray>
        <English>
          <DurationMinimum>2505</DurationMinimum>
          <DurationMaximum>2505</DurationMaximum>
        </English>
        <German>
          <DurationMinimum>2071</DurationMinimum>
          <DurationMaximum>2071</DurationMaximum>
        </German>
        <French>
          <DurationMinimum>2378</DurationMinimum>
          <DurationMaximum>2378</DurationMaximum>
        </French>
        <Russian>
          <DurationMinimum>2609</DurationMinimum>
          <DurationMaximum>2609</DurationMaximum>
        </Russian>
      </DurationLanguageArray>
    </Audio>
    <WwiseStandard>
      <WwiseID>3149725918</WwiseID>
    </WwiseStandard>
  </Values>
</Asset>