<Asset>
  <Template>Audio</Template>
  <Values>
    <Standard>
      <GUID>221503</GUID>
      <Name>Play_AI_DRYQUEEN_IFV_TTP_00002_01QUEEN_8173</Name>
      <IconFilename>test_data/graphics/wwise_icons/event.png</IconFilename>
    </Standard>
    <Audio>
      <DurationLanguageArray>
        <English>
          <DurationMinimum>2686</DurationMinimum>
          <DurationMaximum>2686</DurationMaximum>
        </English>
        <German>
          <DurationMinimum>3471</DurationMinimum>
          <DurationMaximum>3471</DurationMaximum>
        </German>
        <French>
          <DurationMinimum>2918</DurationMinimum>
          <DurationMaximum>2918</DurationMaximum>
        </French>
        <Russian>
          <DurationMinimum>2947</DurationMinimum>
          <DurationMaximum>2947</DurationMaximum>
        </Russian>
      </DurationLanguageArray>
    </Audio>
    <WwiseStandard>
      <WwiseID>4211198302</WwiseID>
    </WwiseStandard>
  </Values>
</Asset>