<Asset>
  <Template>Audio</Template>
  <Values>
    <Standard>
      <GUID>222573</GUID>
      <Name>Play_AI_DRYARTUR_OD3_XXP_00002_01ARTUR_10769</Name>
      <IconFilename>test_data/graphics/wwise_icons/event.png</IconFilename>
    </Standard>
    <Audio>
      <DurationLanguageArray>
        <English>
          <DurationMinimum>3824</DurationMinimum>
          <DurationMaximum>3824</DurationMaximum>
        </English>
        <German>
          <DurationMinimum>5461</DurationMinimum>
          <DurationMaximum>5461</DurationMaximum>
        </German>
        <French>
          <DurationMinimum>3687</DurationMinimum>
          <DurationMaximum>3687</DurationMaximum>
        </French>
        <Russian>
          <DurationMinimum>3597</DurationMinimum>
          <DurationMaximum>3597</DurationMaximum>
        </Russian>
      </DurationLanguageArray>
    </Audio>
    <WwiseStandard>
      <WwiseID>2478562571</WwiseID>
    </WwiseStandard>
  </Values>
</Asset>