<Asset>
  <Template>Audio</Template>
  <Values>
    <Standard>
      <GUID>231186</GUID>
      <Name>Play_AI_DRYNEWAR_ISJLE_ZVYG5_00003_01NEWAR_13640</Name>
      <IconFilename>test_data/graphics/wwise_icons/event.png</IconFilename>
    </Standard>
    <Audio>
      <DurationLanguageArray>
        <English>
          <DurationMinimum>1870</DurationMinimum>
          <DurationMaximum>1870</DurationMaximum>
        </English>
        <German>
          <DurationMinimum>2066</DurationMinimum>
          <DurationMaximum>2066</DurationMaximum>
        </German>
        <French>
          <DurationMinimum>2056</DurationMinimum>
          <DurationMaximum>2056</DurationMaximum>
        </French>
        <Russian>
          <DurationMinimum>2293</DurationMinimum>
          <DurationMaximum>2293</DurationMaximum>
        </Russian>
      </DurationLanguageArray>
    </Audio>
    <WwiseStandard>
      <WwiseID>3298966131</WwiseID>
    </WwiseStandard>
  </Values>
</Asset>