<Asset>
  <Template>Audio</Template>
  <Values>
    <Standard>
      <GUID>232620</GUID>
      <Name>Play_AI_DRYAARHA_CAMPA_33O5E_23WO3_X52JY_00003_01AARHA_17362</Name>
      <IconFilename>test_data/graphics/wwise_icons/event.png</IconFilename>
    </Standard>
    <Audio>
      <DurationLanguageArray>
        <English>
          <DurationMinimum>6312</DurationMinimum>
          <DurationMaximum>6312</DurationMaximum>
        </English>
        <German>
          <DurationMinimum>6570</DurationMinimum>
          <DurationMaximum>6570</DurationMaximum>
        </German>
        <French>
          <DurationMinimum>5672</DurationMinimum>
          <DurationMaximum>5672</DurationMaximum>
        </French>
        <Russian>
          <DurationMinimum>6447</DurationMinimum>
          <DurationMaximum>6447</DurationMaximum>
        </Russian>
      </DurationLanguageArray>
    </Audio>
    <WwiseStandard>
      <WwiseID>1463521679</WwiseID>
    </WwiseStandard>
  </Values>
</Asset>