<Asset>
  <Template>Audio</Template>
  <Values>
    <Standard>
      <GUID>234228</GUID>
      <Name>Play_AI_DRYOLDNA_WGVN5_MRRTO_JMCJO_00001_01OLDNA_16677</Name>
      <IconFilename>test_data/graphics/wwise_icons/event.png</IconFilename>
    </Standard>
    <Audio>
      <DurationLanguageArray>
        <English>
          <DurationMinimum>8808</DurationMinimum>
          <DurationMaximum>8808</DurationMaximum>
        </English>
        <German>
          <DurationMinimum>8808</DurationMinimum>
          <DurationMaximum>8808</DurationMaximum>
        </German>
        <French>
          <DurationMinimum>8808</DurationMinimum>
          <DurationMaximum>8808</DurationMaximum>
        </French>
        <Russian>
          <DurationMinimum>8808</DurationMinimum>
          <DurationMaximum>8808</DurationMaximum>
        </Russian>
      </DurationLanguageArray>
    </Audio>
    <WwiseStandard>
      <WwiseID>837668989</WwiseID>
    </WwiseStandard>
  </Values>
</Asset>