<Asset>
  <Template>Audio</Template>
  <Values>
    <Standard>
      <GUID>234491</GUID>
      <Name>Play_AI_DRYWILLI_0HO_HMO_00005_01WILLI_16852</Name>
      <IconFilename>test_data/graphics/wwise_icons/event.png</IconFilename>
    </Standard>
    <Audio>
      <DurationLanguageArray>
        <English>
          <DurationMinimum>1312</DurationMinimum>
          <DurationMaximum>1312</DurationMaximum>
        </English>
        <German>
          <DurationMinimum>1377</DurationMinimum>
          <DurationMaximum>1377</DurationMaximum>
        </German>
        <French>
          <DurationMinimum>1197</DurationMinimum>
          <DurationMaximum>1197</DurationMaximum>
        </French>
        <Russian>
          <DurationMinimum>1161</DurationMinimum>
          <DurationMaximum>1161</DurationMaximum>
        </Russian>
      </DurationLanguageArray>
    </Audio>
    <WwiseStandard>
      <WwiseID>3684808172</WwiseID>
    </WwiseStandard>
  </Values>
</Asset>