<Asset>
  <Template>Audio</Template>
  <Values>
    <Standard>
      <GUID>237783</GUID>
      <Name>Play_AI_DRYFEM1_Z4P04_00007_01FEM1_19812</Name>
      <IconFilename>test_data/graphics/wwise_icons/event.png</IconFilename>
    </Standard>
    <Audio>
      <DurationLanguageArray>
        <English>
          <DurationMinimum>1325</DurationMinimum>
          <DurationMaximum>1325</DurationMaximum>
        </English>
        <German>
          <DurationMinimum>1445</DurationMinimum>
          <DurationMaximum>1445</DurationMaximum>
        </German>
        <French>
          <DurationMinimum>1311</DurationMinimum>
          <DurationMaximum>1311</DurationMaximum>
        </French>
        <Russian>
          <DurationMinimum>925</DurationMinimum>
          <DurationMaximum>925</DurationMaximum>
        </Russian>
      </DurationLanguageArray>
    </Audio>
    <WwiseStandard>
      <WwiseID>3059900711</WwiseID>
    </WwiseStandard>
  </Values>
</Asset>