<Asset>
  <Template>Audio</Template>
  <Values>
    <Standard>
      <GUID>245409</GUID>
      <Name>Play_AI_DRYTECHN_BASIC_2FNZZ_00004_01TECHN_33804</Name>
      <IconFilename>test_data/graphics/wwise_icons/event.png</IconFilename>
    </Standard>
    <Audio>
      <DurationLanguageArray>
        <English>
          <DurationMinimum>2027</DurationMinimum>
          <DurationMaximum>2027</DurationMaximum>
        </English>
        <German>
          <DurationMinimum>2400</DurationMinimum>
          <DurationMaximum>2400</DurationMaximum>
        </German>
        <French>
          <DurationMinimum>1758</DurationMinimum>
          <DurationMaximum>1758</DurationMaximum>
        </French>
        <Russian>
          <DurationMinimum>1622</DurationMinimum>
          <DurationMaximum>1622</DurationMaximum>
        </Russian>
      </DurationLanguageArray>
    </Audio>
    <WwiseStandard>
      <WwiseID>3428291042</WwiseID>
    </WwiseStandard>
  </Values>
</Asset>