<Asset>
  <Template>Audio</Template>
  <Values>
    <Standard>
      <GUID>245680</GUID>
      <Name>Play_AI_OLDNA_JP2QF_LBHLL_RND</Name>
      <IconFilename>test_data/graphics/wwise_icons/event.png</IconFilename>
    </Standard>
    <Audio>
      <DurationLanguageArray>
        <English>
          <DurationMinimum>8529</DurationMinimum>
          <DurationMaximum>8529</DurationMaximum>
        </English>
        <German>
          <DurationMinimum>8299</DurationMinimum>
          <DurationMaximum>8299</DurationMaximum>
        </German>
        <French>
          <DurationMinimum>8241</DurationMinimum>
          <DurationMaximum>8241</DurationMaximum>
        </French>
        <Russian>
          <DurationMinimum>8256</DurationMinimum>
          <DurationMaximum>8256</DurationMaximum>
        </Russian>
      </DurationLanguageArray>
    </Audio>
    <WwiseStandard>
      <WwiseID>1025894459</WwiseID>
    </WwiseStandard>
  </Values>
</Asset>