<Asset>
  <Template>ExpeditionDecision</Template>
  <Values>
    <Standard>
      <GUID>802187</GUID>
      <Name>Selfless Deeds 1.2.2.2.1.1.1.1.2</Name>
    </Standard>
    <ExpeditionDecision>
      <ChangeMorale>RemoveMedium</ChangeMorale>
      <DecisionVideoSounds>
        <Item>
          <Event>202344</Event>
        </Item>
      </DecisionVideoSounds>
      <DecisionVideo>data/ui/video/expedition/melee_a.bk2</DecisionVideo>
    </ExpeditionDecision>
    <Reward />
    <Text>
      <LocaText>
        <English>
          <Text>&lt;b&gt;Your sailors are overpowered.&lt;/b&gt; The kidnappers have fought much harder battles against much less men, and your crew's attack is dismissed with scorn. They could easily have retrieved the children, but their strange sense of honor makes them consider that goods bought are goods acquired. The crew is sent back to the village with the kids, both looking equally dishevelled and aghast.</Text>
          <Status>Exported</Status>
          <ExportCount>1</ExportCount>
        </English>
      </LocaText>
      <LineID>21038</LineID>
    </Text>
  </Values>
</Asset>