<Asset>
  <Template>ExpeditionDecision</Template>
  <Values>
    <Standard>
      <GUID>803658</GUID>
      <Name>Devil snare 1.1.1.</Name>
    </Standard>
    <ExpeditionDecision>
      <Options>
        <Item>
          <Option>803659</Option>
        </Item>
        <Item>
          <Option>803667</Option>
        </Item>
      </Options>
    </ExpeditionDecision>
    <Reward />
    <Text>
      <LocaText>
        <English>
          <Text>&lt;b&gt;You choose two of your best,&lt;/b&gt; who casually separate themselves from your group. The people in this region are used to western visitors, and suspicions are not raised. Peeking into a cabin, your agents sight &lt;b&gt;a woman being held by two men while a third appears to be forcing her to drink some sort of herbal concoction.&lt;/b&gt;</Text>
          <Status>Exported</Status>
          <ExportCount>1</ExportCount>
        </English>
      </LocaText>
      <LineID>34352</LineID>
    </Text>
  </Values>
</Asset>