<Asset>
  <Template>ExpeditionDecision</Template>
  <Values>
    <Standard>
      <GUID>804075</GUID>
      <Name>Narrow channels 1.2.1.</Name>
    </Standard>
    <ExpeditionDecision />
    <Reward />
    <Text>
      <LocaText>
        <English>
          <Text>Strong men, manage to get to the top of the glacier without too much difficulty, just using ropes and ice pick. Once on top, they are so much higher than the ship that the right way ahead is clear. Note environment clue, map the route to take and go back to the ship. Lead the ship without trouble to the open sea.</Text>
          <Status>GameWriting</Status>
        </English>
      </LocaText>
    </Text>
  </Values>
</Asset>