<Asset>
  <Template>Text</Template>
  <Values>
    <Standard>
      <GUID>111531</GUID>
      <Name>QB_Hugo_Paranoia1</Name>
    </Standard>
    <Text>
      <LocaText>
        <English>
          <Text>Dr. Hugo Mercier feels it, the prying gaze of his old comrade Leon on his every move, waiting for the perfect moment to sell him to the Queen... In order to either confirm or dissipate Mercier's doubts, you must follow the man and see what business he is truly up to.</Text>
          <Status>Exported</Status>
          <ExportCount>3</ExportCount>
        </English>
      </LocaText>
      <LineID>31069</LineID>
    </Text>
  </Values>
</Asset>