<Asset>
  <Template>Text</Template>
  <Values>
    <Standard>
      <GUID>18405</GUID>
      <Name>SmuggleQuest_ArchibaldResponse_ChildrensCharity3_ApologyLetter_HintTextSuccess</Name>
    </Standard>
    <Text>
      <LocaText>
        <English>
          <Text>Oh Bente, you poor dear soul! Those children weren't merely a menace, they were a highly-organised gang of thieves! There's not a bit of silver cutlery left in all of High Clarence Hall!  </Text>
          <Status>Exported</Status>
          <ExportCount>3</ExportCount>
        </English>
      </LocaText>
      <LineID>27272</LineID>
    </Text>
  </Values>
</Asset>