<Asset>
  <Template>A7_QuestStatusQuo</Template>
  <Values>
    <Standard>
      <GUID>114920</GUID>
      <Name>RQ_Explorer_InuitKnowledge</Name>
    </Standard>
    <Quest>
      <InvitationMessage>
        <Notification>
          <IsBaseAutoCreateAsset>1</IsBaseAutoCreateAsset>
          <Values>
            <CharacterNotification>
              <Profile>229</Profile>
              <NotificationTextFemale>21472</NotificationTextFemale>
            </CharacterNotification>
            <BaseNotification>
              <NotificationText>21472</NotificationText>
            </BaseNotification>
            <NotificationSubtitle>
              <Subtitle>115740</Subtitle>
            </NotificationSubtitle>
          </Values>
        </Notification>
      </InvitationMessage>
      <QuestGiver>229</QuestGiver>
      <StoryText>114962</StoryText>
      <QuestCategory>ThePassageQuest</QuestCategory>
      <QuestBookBackground>data/ui/2kimages/main/assets16/questbackground/bg_quest_passage.png</QuestBookBackground>
      <ReputationQuestFail>
        <ReputationFailList />
      </ReputationQuestFail>
      <QuestHints>
        <Item>
          <Text>114982</Text>
        </Item>
      </QuestHints>
      <StarterSpeechBubble>
        <IsBaseAutoCreateAsset>1</IsBaseAutoCreateAsset>
        <Values>
          <Condition />
          <ConditionTutorialInteraction>
            <HintText>114973</HintText>
            <ObjectFilter>
              <IsBaseAutoCreateAsset>1</IsBaseAutoCreateAsset>
              <Values>
                <ObjectFilter>
                  <ObjectGUID>114904</ObjectGUID>
                </ObjectFilter>
              </Values>
            </ObjectFilter>
            <UseSpecificPortrait>1</UseSpecificPortrait>
            <SpecificPortraitProfile>229</SpecificPortraitProfile>
          </ConditionTutorialInteraction>
        </Values>
      </StarterSpeechBubble>
    </Quest>
    <PreConditionList>
      <Condition>
        <Template>ConditionPlayerCounter</Template>
        <Values>
          <Condition />
          <ConditionPlayerCounter>
            <Context>112678</Context>
            <CounterAmount>1</CounterAmount>
            <CounterScope>Session</CounterScope>
          </ConditionPlayerCounter>
        </Values>
      </Condition>
    </PreConditionList>
    <Text>
      <LocaText>
        <English>
          <Text>Inuit Qaujimajatuqangit</Text>
          <Status>Exported</Status>
          <ExportCount>1</ExportCount>
        </English>
      </LocaText>
      <LineID>35173</LineID>
    </Text>
    <Reward>
      <RewardAssets>
        <Item>
          <Reward>193821</Reward>
          <Amount>1</Amount>
          <SentToQuestArea>1</SentToQuestArea>
          <IsDisguised>1</IsDisguised>
        </Item>
      </RewardAssets>
      <RewardReputation />
    </Reward>
    <Objectives>
      <WinConditions>
        <Item>
          <Objective>
            <Template>ItemUsageObjective</Template>
            <Values>
              <ConditionQuestObjective>
                <TextCombinedContextValue>114983</TextCombinedContextValue>
                <QuestTrackerIcon>data/ui/2kimages/main/3dicons/icon_fur_parka.png</QuestTrackerIcon>
              </ConditionQuestObjective>
              <ConditionQuestItemUsed>
                <UseItems>
                  <Item>
                    <Item>116673</Item>
                    <Amount>1</Amount>
                    <TargetObject>112678</TargetObject>
                  </Item>
                </UseItems>
              </ConditionQuestItemUsed>
              <ConditionPropsSessionSettings />
              <ConditionPropsExecutionPlaceSettings>
                <ExecutionPlaceConfirmOnReached>0</ExecutionPlaceConfirmOnReached>
              </ConditionPropsExecutionPlaceSettings>
            </Values>
          </Objective>
        </Item>
      </WinConditions>
    </Objectives>
    <QuestOptional>
      <HasStarterObject>Specific</HasStarterObject>
      <StarterObject>
        <IsBaseAutoCreateAsset>1</IsBaseAutoCreateAsset>
        <Values>
          <Condition />
          <ConditionStarterObject>
            <StarterObjectObject>
              <Template>ConditionObjectSpawnedObject</Template>
              <Values>
                <ConditionObjectSpawnedObject>
                  <ExecutionObject>114904</ExecutionObject>
                  <ObjectSpawnArea>
                    <IsBaseAutoCreateAsset>1</IsBaseAutoCreateAsset>
                    <Values>
                      <SpawnArea>
                        <SpawnContext>Area</SpawnContext>
                        <MatcherGUID>114898</MatcherGUID>
                        <LimitToQuestArea>1</LimitToQuestArea>
                        <DistanceToContext>5</DistanceToContext>
                        <DistanceToBorder>Near</DistanceToBorder>
                        <DistanceToIsland>Far</DistanceToIsland>
                      </SpawnArea>
                    </Values>
                  </ObjectSpawnArea>
                </ConditionObjectSpawnedObject>
                <ConditionScanner />
                <ConditionObjectiveSignsAndFeedback />
              </Values>
            </StarterObjectObject>
          </ConditionStarterObject>
          <ConditionQuestObjective>
            <ObjectiveSignsAndFeedback>
              <IsBaseAutoCreateAsset>1</IsBaseAutoCreateAsset>
              <Values>
                <ConditionObjectiveSignsAndFeedback>
                  <Infolayer>501006</Infolayer>
                </ConditionObjectiveSignsAndFeedback>
              </Values>
            </ObjectiveSignsAndFeedback>
          </ConditionQuestObjective>
          <ConditionPropsSessionSettings />
        </Values>
      </StarterObject>
    </QuestOptional>
  </Values>
</Asset>